BetSim/__init__.py
BetSim/simulator.py
BetSim-0.0.1.dist-info/LICENSE
BetSim-0.0.1.dist-info/METADATA
BetSim-0.0.1.dist-info/WHEEL
BetSim-0.0.1.dist-info/top_level.txt
BetSim-0.0.1.dist-info/RECORD
